tests/__init__.py
tests/test_manual.py
tests/test_snapi.py
yapi/__init__.py
yapi/yapiClient.py
yapi/inquisit/__init__.py
yapi/inquisit/inquisitClient.py
yapi/meta/__init__.py
yapi/meta/email.py
yapi/meta/playwright.py
yapi/meta/utilities.py
yapi/redcap/__init__.py
yapi/redcap/redcapClient.py
yapi/sleep_studies/__init__.py
yapi/sleep_studies/report_utilities.py
yapi/sleep_studies/sleep_studies.py
yapi/snapi/__init__.py
yapi/snapi/objects/__init__.py
yapi/snapi/objects/participants.py
yapi/snapi/objects/studies.py
yapi/snapi/objects/users.py
yapi/snapi/objects/withings/__init__.py
yapi/snapi/objects/withings/withings.py
yapi/snapi/objects/withings/mixins/__init__.py
yapi/snapi/objects/withings/mixins/sleep.py
yapi/snapi/objects/withings/mixins/user.py
yapi/snapi/objects/withings/mixins/functions/__init__.py
yapi/utilities/__init__.py
yapi/utilities/epoch.py
yapi/utilities/w_download.py
yawn_api-0.1.3.dist-info/LICENSE
yawn_api-0.1.3.dist-info/METADATA
yawn_api-0.1.3.dist-info/WHEEL
yawn_api-0.1.3.dist-info/top_level.txt
yawn_api-0.1.3.dist-info/RECORD
