Metadata-Version: 2.1
Name: yawn-api
Version: 0.1.3
Summary: A Python package for interacting with the SNAPI API, YawnLabs, and various other health device APIs.
Home-page: https://github.com/jackmanners/yawn-api
Author: Jack Manners
Author-email: jack.manners@flinders.edu.au
Classifier: Programming Language :: Python :: 3
Classifier: License :: OSI Approved :: MIT License
Classifier: Operating System :: OS Independent
Requires-Python: >=3.6
License-File: LICENSE
Requires-Dist: pandas
Requires-Dist: numpy
Requires-Dist: requests
Requires-Dist: python-dotenv
